eventcore_kafka
