Metadata-Version: 1.0
Name: eventcore-kafka
Version: 0.3.2
Summary: Produce and consume events with Kafka.
Home-page: https://github.com/maikelboogerd/eventcore-kafka
Author: Maikel van den Boogerd
Author-email: maikelboogerd@gmail.com
License: MIT
Keywords: event,kafka,producer,consumer
Platform: UNKNOWN
